<?xml version="1.0" encoding="utf-8" ?><dwsync><file name="loader.gif" server="sv7028.xserver.jp//newpacific.info/public_html/" local="3689389200" remote="3689389200" Dst="-1" /><file name="logo-dark.png" server="sv7028.xserver.jp//newpacific.info/public_html/" local="3689389200" remote="3689389200" Dst="-1" /><file name="logo-dark2.png" server="sv7028.xserver.jp//newpacific.info/public_html/" local="3689389200" remote="3689389200" Dst="-1" /><file name="logo-dark4 2.png" server="sv7028.xserver.jp//newpacific.info/public_html/" local="3689389200" remote="3689389200" Dst="-1" /><file name="logo-dark4.png" server="sv7028.xserver.jp//newpacific.info/public_html/" local="3689389200" remote="3689389200" Dst="-1" /><file name="logo-light-border.png" server="sv7028.xserver.jp//newpacific.info/public_html/" local="3689389200" remote="3689389200" Dst="-1" /><file name="logo-light.png" server="sv7028.xserver.jp//newpacific.info/public_html/" local="3689389200" remote="3689389200" Dst="-1" /><file name="logo-light1.png" server="sv7028.xserver.jp//newpacific.info/public_html/" local="3689389200" remote="3689389200" Dst="-1" /><file name="logo-light2.png" server="sv7028.xserver.jp//newpacific.info/public_html/" local="3689389200" remote="3689389200" Dst="-1" /><file name="logo-smaller.png" server="sv7028.xserver.jp//newpacific.info/public_html/" local="3689389200" remote="3689389200" Dst="-1" /><file name="logo.psd" server="sv7028.xserver.jp//newpacific.info/public_html/" local="3689389200" remote="3689389200" Dst="-1" /><file name="map-marker 1.png" server="sv7028.xserver.jp//newpacific.info/public_html/" local="3689389200" remote="3689389200" Dst="-1" /><file name="map-marker.png" server="sv7028.xserver.jp//newpacific.info/public_html/" local="3689389200" remote="3689389200" Dst="-1" /></dwsync>